_dacsagb.so
dacsagb.py
etrflib/__init__.py
etrflib/main.py
etrflib-0.1.3.dist-info/entry_points.txt
etrflib-0.1.3.dist-info/WHEEL
etrflib-0.1.3.dist-info/METADATA
etrflib-0.1.3.dist-info/RECORD
