Metadata-Version: 2.1
Name: etrflib
Version: 0.1.3
Summary: 
Author: Francesco Bartoli
Author-email: francesco.bartoli@geobeyond.it
Requires-Python: >=3.8,<4.0
Classifier: Programming Language :: Python :: 3
Classifier: Programming Language :: Python :: 3.10
Classifier: Programming Language :: Python :: 3.8
Classifier: Programming Language :: Python :: 3.9
Requires-Dist: aiofiles (>=22.1.0,<23.0.0)
Requires-Dist: cffi (>=1.15.0,<2.0.0)
Requires-Dist: ipython (>=8.3.0,<9.0.0)
Requires-Dist: miniopy-async (>=1.11,<2.0)
Requires-Dist: pydantic (>=1.10.2,<2.0.0)
Requires-Dist: pydffi (>=0.9.3,<0.10.0)
Requires-Dist: pyfiglet (>=0.8.post1,<0.9)
Requires-Dist: typer[all] (>=0.7.0,<0.8.0)
Project-URL: Bug Tracker, https://github.com/catasto-open/etrflib/issues
Project-URL: Code, https://github.com/catasto-open/etrflib
Project-URL: Documentation, https://etrflib.readthedocs.io/en/latest
